RAM/design.sv
//Prajwal Kadam
`timescale 1ns / 1ps
module RAM( dataIn,
                dataOut,
                Addr, 
                CS, 
                WRITE, 
                READ, 
                clk
              );
// parameters for the width 
parameter ADR   = 10;
parameter DATA   = 8;
parameter MS  = 1024;
//ports
  input   [DATA-1:0]  dataIn;
output reg [DATA-1:0]  dataOut;
input   [ADR-1:0]  Addr;
input CS, 
      WRITE, 
      READ, 
      clk;
     
//internal variables
reg [DATA-1:0] RAM [MS-1:0];
always @ (posedge clk)
begin
 if (CS == 1'b1) begin
  if (WRITE == 1'b1 && READ == 1'b0) begin
   RAM [Addr] = dataIn;
  end
  else if (READ == 1'b1 && WRITE == 1'b0) begin
   dataOut = RAM [Addr]; 
  end
  else;
 end
 else;
end
endmodule

RAM/testbench.sv
`timescale 1ns / 1ps
module RAM_tb;
 // Inputs
 reg [7:0] dataIn;
 reg [9:0] Addr;
 reg CS;
 reg WRITE;
 reg READ;
 reg clk;
 // Outputs
 wire [7:0] dataOut;
 // Instantiate the Unit Under Test (UUT)
 RAM uut (
  .dataIn(dataIn), 
  .dataOut(dataOut), 
  .Addr(Addr), 
  .CS(CS), 
  .WRITE(WRITE), 
  .READ(READ), 
  .clk(clk)
  );
 initial begin
  // Initialize Inputs
  dataIn  = 8'h0;
  Addr  = 8'h0;
  CS  = 1'b0;
  WRITE  = 1'b0;
  READ  = 1'b0;
  clk  = 1'b0;
  // Wait 100 ns for global reset to finish
  #100;
  // Add stimulus here
  dataIn  = 8'h0;
  Addr  = 8'h0;
  CS  = 1'b1;
  WRITE  = 1'b1;
  READ  = 1'b0;
  #20;
  dataIn  = 8'h1;
  Addr  = 8'h0;
  #20;
  dataIn  = 8'h12;
  Addr  = 8'h1;
  #20;
  dataIn  = 8'h13;
  Addr  = 8'h2;
  #20;
  dataIn  = 8'h16;
  Addr  = 8'h3;
  #20;
  dataIn  = 8'h2;
  Addr  = 8'h4;
  #40;
  Addr  = 8'h0;
  WRITE  = 1'b0;
  READ  = 1'b1;
  #20;
  Addr   = 8'h1;
  #20;
  Addr   = 8'h2;
  #20;
  Addr   = 8'h3;
  #20;
  Addr   = 8'h4;
 end
 always #10 clk = ~ clk;
initial begin
		$dumpfile("dump.vcd");
		$dumpvars;
		#400 $finish;
  		end 
endmodule

RAM/dump.vcd
$date
	Thu Aug  4 08:50:06 2022
$end
$version
	Icarus Verilog
$end
$timescale
	1ps
$end
$scope module RAM_tb $end
$var wire 8 ! dataOut [7:0] $end
$var reg 10 " Addr [9:0] $end
$var reg 1 # CS $end
$var reg 1 $ READ $end
$var reg 1 % WRITE $end
$var reg 1 & clk $end
$var reg 8 ' dataIn [7:0] $end
$scope module uut $end
$var wire 10 ( Addr [9:0] $end
$var wire 1 ) CS $end
$var wire 1 * READ $end
$var wire 1 + WRITE $end
$var wire 1 , clk $end
$var wire 8 - dataIn [7:0] $end
$var reg 8 . dataOut [7:0] $end
$upscope $end
$upscope $end
$enddefinitions $end
#0
$dumpvars
bx .
b0 -
0,
0+
0*
0)
b0 (
b0 '
0&
0%
0$
0#
b0 "
bx !
$end
#10000
1&
1,
#20000
0&
0,
#30000
1&
1,
#40000
0&
0,
#50000
1&
1,
#60000
0&
0,
#70000
1&
1,
#80000
0&
0,
#90000
1&
1,
#100000
0&
0,
1%
1+
1#
1)
#110000
1&
1,
#120000
0&
0,
b1 '
b1 -
#130000
1&
1,
#140000
0&
0,
b1 "
b1 (
b10010 '
b10010 -
#150000
1&
1,
#160000
0&
0,
b10 "
b10 (
b10011 '
b10011 -
#170000
1&
1,
#180000
0&
0,
b11 "
b11 (
b10110 '
b10110 -
#190000
1&
1,
#200000
0&
0,
b100 "
b100 (
b10 '
b10 -
#210000
1&
1,
#220000
0&
0,
#230000
1&
1,
#240000
0&
0,
1$
1*
0%
0+
b0 "
b0 (
#250000
b1 .
b1 !
1&
1,
#260000
0&
0,
b1 "
b1 (
#270000
b10010 .
b10010 !
1&
1,
#280000
0&
0,
b10 "
b10 (
#290000
b10011 .
b10011 !
1&
1,
#300000
0&
0,
b11 "
b11 (
#310000
b10110 .
b10110 !
1&
1,
#320000
0&
0,
b100 "
b100 (
#330000
b10 .
b10 !
1&
1,
