ParityChecker/design.sv

module parity_gen (x, clk, z); 
input x, clk; 
output reg z; 
reg state; // The machine state 
parameter EVEN=0, ODD=1; 
always @(posedge clk) 
	case (state) 
		EVEN: begin 
		z <= x ? 1 : 0; 
		state <= x ? ODD : EVEN; 
		end 
		ODD: begin 
		z <= x ? 0 : 1; 
		state <= x ? EVEN : ODD; 
		end 
		default: state <= EVEN; 
	endcase 
endmodule

ParityChecker/testbench.sv
module test_parity; 
reg clk, x; wire z; 
parity_gen PAR (x, clk, z); 
initial 
begin 
  clk = 1'b0; 
end 
always #5 clk = ~clk; 
initial 
begin 
# 2 x = 0; #10 x = 1; #10 x = 1; #10 x = 1; 
#10 x = 0; #10 x = 1; #10 x = 0; #10 x = 0; 
#10 x = 0; #10 x = 1; #10 x = 1; #10 x = 0;
#10 x = 1; #10 x = 1; #10 x = 1; #10 x = 1; 
#10 x = 0; #10 x = 0; #10 x = 0; #10 x = 0; 
#10 $finish; 
end
  initial begin
		$dumpfile("dump.vcd");
		$dumpvars;
		#200 $finish;
  		end
endmodule

ParityChecker/dump.vcd
$date
	Thu Aug  4 09:00:59 2022
$end
$version
	Icarus Verilog
$end
$timescale
	1s
$end
$scope module test_parity $end
$var wire 1 ! z $end
$var reg 1 " clk $end
$var reg 1 # x $end
$scope module PAR $end
$var wire 1 $ clk $end
$var wire 1 % x $end
$var reg 1 & state $end
$var reg 1 ' z $end
$upscope $end
$upscope $end
$enddefinitions $end
#0
$dumpvars
x'
x&
x%
0$
x#
0"
x!
$end
#2
0#
0%
#5
0&
1"
1$
#10
0"
0$
#12
1#
1%
#15
1&
1'
1!
1"
1$
#20
0"
0$
#25
0&
0'
0!
1"
1$
#30
0"
0$
#35
1&
1'
1!
1"
1$
#40
0"
0$
#42
0#
0%
#45
1"
1$
#50
0"
0$
#52
1#
1%
#55
0&
0'
0!
1"
1$
#60
0"
0$
#62
0#
0%
#65
1"
1$
#70
0"
0$
#75
1"
1$
#80
0"
0$
#85
1"
1$
#90
0"
0$
#92
1#
1%
#95
1&
1'
1!
1"
1$
#100
0"
0$
#105
0&
0'
0!
1"
1$
#110
0"
0$
#112
0#
0%
#115
1"
1$
#120
0"
0$
#122
1#
1%
#125
1&
1'
1!
1"
1$
#130
0"
0$
#135
0&
0'
0!
1"
1$
#140
0"
0$
#145
1&
1'
1!
1"
1$
#150
0"
0$
#155
0&
0'
0!
1"
1$
#160
0"
0$
#162
0#
0%
