Car_Parking_Project/design.sv

`timescale 1ns / 1ps
module parking( 
	input clk,rst,
	input entry, exit, //sensors at both end 
 	input [1:0] password1, password2,
 	output wire GREEN,RED,
 	output reg [6:0] HEX_1, HEX_2
    );
 
parameter IDLE = 3'b000,WAIT_PASSWORD = 3'b001,WRONG_PASS = 3'b010,RIGHT_PASS = 3'b011,STOP = 3'b100;
 
//moore fsm as output depends on current state
reg[2:0] current_state, next_state;
reg[31:0] counter_wait;
reg red_tmp,green_tmp;
// next state
always @(posedge clk or negedge rst)
begin
if(~rst) 
	current_state = IDLE;
else
	current_state = next_state;
end
// counter_wait
always @(posedge clk or negedge rst) 
begin
 if(~rst) 
 	counter_wait <= 0;
 else if(current_state==WAIT_PASSWORD)
 	counter_wait <= counter_wait + 1;
 else 
 	counter_wait <= 0;
end
 // change state

always @(*)
begin
 case(current_state)
 IDLE: begin
   		if(entry == 1) //entry sensor high
 		 next_state = WAIT_PASSWORD;
 		else
 		 next_state = IDLE;
 	   end
 WAIT_PASSWORD: begin
 		if(counter_wait <= 3)
 			next_state = WAIT_PASSWORD;
 		else 
 		begin
 		 if((password1==2'b01)&&(password2==2'b10))
 		 next_state = RIGHT_PASS;
 		 else
 		 next_state = WRONG_PASS;
 		end
 		end
 WRONG_PASS: begin
		 if((password1==2'b01)&&(password2==2'b10))
		 next_state = RIGHT_PASS;
		 else
		 next_state = WRONG_PASS;
		 end
 RIGHT_PASS: begin
   		if(entry ==1 && exit == 1)
		 next_state = STOP;
 		else if(exit == 1)
 		 next_state = IDLE;
		else
		 next_state = RIGHT_PASS;
		end
 STOP: begin
		if((password1==2'b01)&&(password2==2'b10))
		next_state = RIGHT_PASS;
		else
		next_state = STOP;
		end
 		default: next_state = IDLE;
endcase
end
 // LEDs and output
always @(posedge clk) begin 
 case(current_state)
 IDLE: begin
	 green_tmp = 1'b0;
	 red_tmp = 1'b0;
	 HEX_1 = 7'b1111111; // off
	 HEX_2 = 7'b1111111; // off
	end
 WAIT_PASSWORD: begin
	 green_tmp = 1'b0;
	 red_tmp = 1'b1;
	 HEX_1 = 7'b0000110; // E
	 HEX_2 = 7'b0101011; // n 
	end
 WRONG_PASS: begin
	 green_tmp = 1'b0;
	 red_tmp = ~red_tmp;
	 HEX_1 = 7'b0000110; // E
	 HEX_2 = 7'b0000110; // E 
	end
 RIGHT_PASS: begin
	 green_tmp = ~green_tmp;
	 red_tmp = 1'b0;
	 HEX_1 = 7'b0000010; // 6
	 HEX_2 = 7'b1000000; // 0 
	end
 STOP: begin
	 green_tmp = 1'b0;
	 red_tmp = ~red_tmp;
	 HEX_1 = 7'b0010010; // 5
	 HEX_2 = 7'b0001100; // P 
	end
endcase
end
assign RED = red_tmp  ;
assign GREEN = green_tmp;
endmodule

Car_Parking_Project/testbench.sv
//There are 2 sensors at entry and exit which are triggered by a coming vehicle until then system remains idle.When its triggered it asks for password to open gate.Gate opens for right password and remains close for wrong one. When password is right the green led blinks. When condition is wait password the led remains red and for wrong password it blinks red led.If 2 cars triggered sensor simultaneouly then gate remains close till entering car enters right password.
module tb_parking;

  reg clk;	// Inputs
  reg rst;
  reg entry;
  reg exit;
  reg [1:0] password1;
  reg [1:0] password2;

  // Outputs
  wire GREEN; //led green
  wire RED;
  wire [6:0] HEX_1;
  wire [6:0] HEX_2;

  // Instantiate the Unit Under Test (UUT)
  parking uut (.clk(clk), 
  				.rst(rst), 
     			.entry(entry), 
  				.exit(exit), 
  				.password1(password1), 
  				.password2(password2), 
  				.GREEN(GREEN), 
  				.RED(RED), 
  				.HEX_1(HEX_1), 
 				.HEX_2(HEX_2)
 				);
 initial begin
 clk = 0;
 forever #10 clk = ~clk;
 end
 initial begin
 // Initialize Inputs
 rst = 0;
 entry= 0;
 exit = 0;
 password1 = 2'b00;
 password2 = 2'b00;
 // Wait 100 ns for global reset to finish
 #100;
 rst= 1;
 #20;
 entry=1;
 #1000;
 entry=0;
 password1 = 2'b01;
 password2 = 2'b10;
 #2000;
 exit =1;
 
 end
  initial begin
		$dumpfile("dump.vcd");
		$dumpvars;
		#4000 $finish;
  		end    
endmodule

Car_Parking_Project/dump.vcd
$date
	Thu Aug  4 08:34:58 2022
$end
$version
	Icarus Verilog
$end
$timescale
	1ps
$end
$scope module tb_parking $end
$var wire 1 ! GREEN $end
$var wire 7 " HEX_1 [6:0] $end
$var wire 7 # HEX_2 [6:0] $end
$var wire 1 $ RED $end
$var reg 1 % clk $end
$var reg 1 & entry $end
$var reg 1 ' exit $end
$var reg 2 ( password1 [1:0] $end
$var reg 2 ) password2 [1:0] $end
$var reg 1 * rst $end
$scope module uut $end
$var wire 1 ! GREEN $end
$var wire 1 $ RED $end
$var wire 1 + clk $end
$var wire 1 , entry $end
$var wire 1 - exit $end
$var wire 2 . password1 [1:0] $end
$var wire 2 / password2 [1:0] $end
$var wire 1 0 rst $end
$var reg 7 1 HEX_1 [6:0] $end
$var reg 7 2 HEX_2 [6:0] $end
$var reg 32 3 counter_wait [31:0] $end
$var reg 3 4 current_state [2:0] $end
$var reg 1 5 green_tmp $end
$var reg 3 6 next_state [2:0] $end
$var reg 1 7 red_tmp $end
$upscope $end
$upscope $end
$enddefinitions $end
#0
$dumpvars
x7
b0 6
x5
b0 4
b0 3
bx 2
bx 1
00
b0 /
b0 .
0-
0,
0+
0*
b0 )
b0 (
0'
0&
0%
x$
bx #
bx "
x!
$end
#10000
b1111111 2
b1111111 #
b1111111 1
b1111111 "
07
0$
05
0!
1%
1+
#20000
0%
0+
#30000
1%
1+
#40000
0%
0+
#50000
1%
1+
#60000
0%
0+
#70000
1%
1+
#80000
0%
0+
#90000
1%
1+
#100000
0%
0+
1*
10
#110000
1%
1+
#120000
b1 6
0%
0+
1&
1,
#130000
b1 3
b101011 2
b101011 #
b110 1
b110 "
17
1$
b1 4
1%
1+
#140000
0%
0+
#150000
b10 3
1%
1+
#160000
0%
0+
#170000
b11 3
1%
1+
#180000
0%
0+
#190000
b10 6
b100 3
1%
1+
#200000
0%
0+
#210000
b0 3
b110 2
b110 #
07
0$
b10 4
1%
1+
#220000
0%
0+
#230000
17
1$
1%
1+
#240000
0%
0+
#250000
07
0$
1%
1+
#260000
0%
0+
#270000
17
1$
1%
1+
#280000
0%
0+
#290000
07
0$
1%
1+
#300000
0%
0+
#310000
17
1$
1%
1+
#320000
0%
0+
#330000
07
0$
1%
1+
#340000
0%
0+
#350000
17
1$
1%
1+
#360000
0%
0+
#370000
07
0$
1%
1+
#380000
0%
0+
#390000
17
1$
1%
1+
#400000
0%
0+
#410000
07
0$
1%
1+
#420000
0%
0+
#430000
17
1$
1%
1+
#440000
0%
0+
#450000
07
0$
1%
1+
#460000
0%
0+
#470000
17
1$
1%
1+
#480000
0%
0+
#490000
07
0$
1%
1+
#500000
0%
0+
#510000
17
1$
1%
1+
#520000
0%
0+
#530000
07
0$
1%
1+
#540000
0%
0+
#550000
17
1$
1%
1+
#560000
0%
0+
#570000
07
0$
1%
1+
#580000
0%
0+
#590000
17
1$
1%
1+
#600000
0%
0+
#610000
07
0$
1%
1+
#620000
0%
0+
#630000
17
1$
1%
1+
#640000
0%
0+
#650000
07
0$
1%
1+
#660000
0%
0+
#670000
17
1$
1%
1+
#680000
0%
0+
#690000
07
0$
1%
1+
#700000
0%
0+
#710000
17
1$
1%
1+
#720000
0%
0+
#730000
07
0$
1%
1+
#740000
0%
0+
#750000
17
1$
1%
1+
#760000
0%
0+
#770000
07
0$
1%
1+
#780000
0%
0+
#790000
17
1$
1%
1+
#800000
0%
0+
#810000
07
0$
1%
1+
#820000
0%
0+
#830000
17
1$
1%
1+
#840000
0%
0+
#850000
07
0$
1%
1+
#860000
0%
0+
#870000
17
1$
1%
1+
#880000
0%
0+
#890000
07
0$
1%
1+
#900000
0%
0+
#910000
17
1$
1%
1+
#920000
0%
0+
#930000
07
0$
1%
1+
#940000
0%
0+
#950000
17
1$
1%
1+
#960000
0%
0+
#970000
07
0$
1%
1+
#980000
0%
0+
#990000
17
1$
1%
1+
#1000000
0%
0+
#1010000
07
0$
1%
1+
#1020000
0%
0+
#1030000
17
1$
1%
1+
#1040000
0%
0+
#1050000
07
0$
1%
1+
#1060000
0%
0+
#1070000
17
1$
1%
1+
#1080000
0%
0+
#1090000
07
0$
1%
1+
#1100000
0%
0+
#1110000
17
1$
1%
1+
#1120000
b11 6
0%
0+
b10 )
b10 /
b1 (
b1 .
0&
0,
#1130000
b1000000 2
b1000000 #
b10 1
b10 "
07
0$
15
1!
b11 4
1%
1+
#1140000
0%
0+
#1150000
05
0!
1%
1+
#1160000
0%
0+
#1170000
15
1!
1%
1+
#1180000
0%
0+
#1190000
05
0!
1%
1+
#1200000
0%
0+
#1210000
15
1!
1%
1+
#1220000
0%
0+
#1230000
05
0!
1%
1+
#1240000
0%
0+
#1250000
15
1!
1%
1+
#1260000
0%
0+
#1270000
05
0!
1%
1+
#1280000
0%
0+
#1290000
15
1!
1%
1+
#1300000
0%
0+
#1310000
05
0!
1%
1+
#1320000
0%
0+
#1330000
15
1!
1%
1+
#1340000
0%
0+
#1350000
05
0!
1%
1+
#1360000
0%
0+
#1370000
15
1!
1%
1+
#1380000
0%
0+
#1390000
05
0!
1%
1+
#1400000
0%
0+
#1410000
15
1!
1%
1+
#1420000
0%
0+
#1430000
05
0!
1%
1+
#1440000
0%
0+
#1450000
15
1!
1%
1+
#1460000
0%
0+
#1470000
05
0!
1%
1+
#1480000
0%
0+
#1490000
15
1!
1%
1+
#1500000
0%
0+
#1510000
05
0!
1%
1+
#1520000
0%
0+
#1530000
15
1!
1%
1+
#1540000
0%
0+
#1550000
05
0!
1%
1+
#1560000
0%
0+
#1570000
15
1!
1%
1+
#1580000
0%
0+
#1590000
05
0!
1%
1+
#1600000
0%
0+
#1610000
15
1!
1%
1+
#1620000
0%
0+
#1630000
05
0!
1%
1+
#1640000
0%
0+
#1650000
15
1!
1%
1+
#1660000
0%
0+
#1670000
05
0!
1%
1+
#1680000
0%
0+
#1690000
15
1!
1%
1+
#1700000
0%
0+
#1710000
05
0!
1%
1+
#1720000
0%
0+
#1730000
15
1!
1%
1+
#1740000
0%
0+
#1750000
05
0!
1%
1+
#1760000
0%
0+
#1770000
15
1!
1%
1+
#1780000
0%
0+
#1790000
05
0!
1%
1+
#1800000
0%
0+
#1810000
15
1!
1%
1+
#1820000
0%
0+
#1830000
05
0!
1%
1+
#1840000
0%
0+
#1850000
15
1!
1%
1+
#1860000
0%
0+
#1870000
05
0!
1%
1+
#1880000
0%
0+
#1890000
15
1!
1%
1+
#1900000
0%
0+
#1910000
05
0!
1%
1+
#1920000
0%
0+
#1930000
15
1!
1%
1+
#1940000
0%
0+
#1950000
05
0!
1%
1+
#1960000
0%
0+
#1970000
15
1!
1%
1+
#1980000
0%
0+
#1990000
05
0!
1%
1+
#2000000
0%
0+
#2010000
15
1!
1%
1+
#2020000
0%
0+
#2030000
05
0!
1%
1+
#2040000
0%
0+
#2050000
15
1!
1%
1+
#2060000
0%
0+
#2070000
05
0!
1%
1+
#2080000
0%
0+
#2090000
15
1!
1%
1+
#2100000
0%
0+
#2110000
05
0!
1%
1+
#2120000
0%
0+
#2130000
15
1!
1%
1+
#2140000
0%
0+
#2150000
05
0!
1%
1+
#2160000
0%
0+
#2170000
15
1!
1%
1+
#2180000
0%
0+
#2190000
05
0!
1%
1+
#2200000
0%
0+
#2210000
15
1!
1%
1+
#2220000
0%
0+
#2230000
05
0!
1%
1+
#2240000
0%
0+
#2250000
15
1!
1%
1+
#2260000
0%
0+
#2270000
05
0!
1%
1+
#2280000
0%
0+
#2290000
15
1!
1%
1+
#2300000
0%
0+
#2310000
05
0!
1%
1+
#2320000
0%
0+
#2330000
15
1!
1%
1+
#2340000
0%
0+
#2350000
05
0!
1%
1+
#2360000
0%
0+
#2370000
15
1!
1%
1+
#2380000
0%
0+
#2390000
05
0!
1%
1+
#2400000
0%
0+
#2410000
15
1!
1%
1+
#2420000
0%
0+
#2430000
05
0!
1%
1+
#2440000
0%
0+
#2450000
15
1!
1%
1+
#2460000
0%
0+
#2470000
05
0!
1%
1+
#2480000
0%
0+
#2490000
15
1!
1%
1+
#2500000
0%
0+
#2510000
05
0!
1%
1+
#2520000
0%
0+
#2530000
15
1!
1%
1+
#2540000
0%
0+
#2550000
05
0!
1%
1+
#2560000
0%
0+
#2570000
15
1!
1%
1+
#2580000
0%
0+
#2590000
05
0!
1%
1+
#2600000
0%
0+
#2610000
15
1!
1%
1+
#2620000
0%
0+
#2630000
05
0!
1%
1+
#2640000
0%
0+
#2650000
15
1!
1%
1+
#2660000
0%
0+
#2670000
05
0!
1%
1+
#2680000
0%
0+
#2690000
15
1!
1%
1+
#2700000
0%
0+
#2710000
05
0!
1%
1+
#2720000
0%
0+
#2730000
15
1!
1%
1+
#2740000
0%
0+
#2750000
05
0!
1%
1+
#2760000
0%
0+
#2770000
15
1!
1%
1+
#2780000
0%
0+
#2790000
05
0!
1%
1+
#2800000
0%
0+
#2810000
15
1!
1%
1+
#2820000
0%
0+
#2830000
05
0!
1%
1+
#2840000
0%
0+
#2850000
15
1!
1%
1+
#2860000
0%
0+
#2870000
05
0!
1%
1+
#2880000
0%
0+
#2890000
15
1!
1%
1+
#2900000
0%
0+
#2910000
05
0!
1%
1+
#2920000
0%
0+
#2930000
15
1!
1%
1+
#2940000
0%
0+
#2950000
05
0!
1%
1+
#2960000
0%
0+
#2970000
15
1!
1%
1+
#2980000
0%
0+
#2990000
05
0!
1%
1+
#3000000
0%
0+
#3010000
15
1!
1%
1+
#3020000
0%
0+
#3030000
05
0!
1%
1+
#3040000
0%
0+
#3050000
15
1!
1%
1+
#3060000
0%
0+
#3070000
05
0!
1%
1+
#3080000
0%
0+
#3090000
15
1!
1%
1+
#3100000
0%
0+
#3110000
05
0!
1%
1+
#3120000
b0 6
0%
0+
1'
1-
#3130000
b1111111 2
b1111111 #
b1111111 1
b1111111 "
b0 4
1%
1+
