SequenceDetector/design.sv

module seq10101 (in, out, clk, reset);
	
	parameter S0 = 3'b000; 
	parameter S1 = 3'b001;
	parameter S2 = 3'b010;
	parameter S3 = 3'b011;
	parameter S4 = 3'b100;
	
	input clk,reset,in;//input and output
	output reg out;

	reg [2:0] state;
	reg [2:0] next_state;//registered state
	
	always @ (posedge clk)//state switching
	if(reset) 
		state <= S0;
	else 
		state <= next_state;
	
	
	always @ (in or state)
	begin
		case(state)
		S0:
			begin
			if (in) 
				begin
				next_state <= S1;
				out = 1'b0;
				end
			else
			    begin
				next_state <= S0;
				out = 1'b0;
				end
		    end
		S1:begin
			if (in) begin
				next_state <= S1;
				out = 1'b0;
				end
			else begin
				next_state <= S2;
				out = 1'b0;
				end
		   end
		S2:begin
			if (in) begin 
				next_state <= S3;
				out = 1'b0;
				end
			else begin
				next_state <= S0;
				out = 1'b0;
				end
		   end
		S3:begin
			if (in) begin
				next_state <= S1;
				out = 1'b0;
				end
			else begin
				next_state <= S4;
				out = 1'b0;
				end
		   end
		S4:begin
			if (in) begin
				next_state <= S1;
				out = 1'b1;
				end
			else begin
				next_state <= S0;
				out = 1'b0;
				end
		   end
		endcase
	end
endmodule

SequenceDetector/testbench.sv
module eq10101_tb();
	wire out;
	wire state,next_state;
	reg in;
	reg clk,reset;
seq10101 uut( 	.in(in),
		    .out(out),
            .clk(clk),
		    .reset(reset));
	initial 
	begin //time
		clk = 0;
		forever #5 clk = ~clk;
	 end
	
	initial
		begin
			in = 0;
			reset = 1;
			#20 reset = 0;
			
			#5 in = 1;#10 in = 0;#10 in = 1;
			#10 in = 0;#10 in = 1;#10 in = 0;
			#10 in = 1;#10 in = 1;#10 in = 1;
			#10 in = 1;#10 in = 0;#10 in = 1;
			#10 in = 1;#10 in = 1;#10 in = 1;
			#10 in = 1;#10 in = 0;#10 in = 1;
			#10 in = 0;#10 in = 1;#10 in = 0;
		end
	initial begin
		$dumpfile("dump.vcd");
		$dumpvars;
		#300 $finish;
  		end
endmodule

SequenceDetector/dump.vcd
$date
	Thu Aug  4 08:55:32 2022
$end
$version
	Icarus Verilog
$end
$timescale
	1s
$end
$scope module eq10101_tb $end
$var wire 1 ! out $end
$var reg 1 " clk $end
$var reg 1 # in $end
$var reg 1 $ reset $end
$scope module uut $end
$var wire 1 % clk $end
$var wire 1 & in $end
$var wire 1 ' reset $end
$var reg 3 ( next_state [2:0] $end
$var reg 1 ) out $end
$var reg 3 * state [2:0] $end
$upscope $end
$upscope $end
$enddefinitions $end
#0
$dumpvars
bx *
x)
bx (
1'
0&
0%
1$
0#
0"
x!
$end
#5
b0 (
0)
0!
b0 *
1"
1%
#10
0"
0%
#15
1"
1%
#20
0"
0%
0$
0'
#25
b1 (
1"
1%
1#
1&
#30
0"
0%
#35
b1 *
b10 (
1"
1%
0#
0&
#40
0"
0%
#45
b10 *
b11 (
1"
1%
1#
1&
#50
0"
0%
#55
b11 *
b100 (
1"
1%
0#
0&
#60
0"
0%
#65
1)
1!
b100 *
b1 (
1"
1%
1#
1&
#70
0"
0%
#75
b1 *
b10 (
0)
0!
1"
1%
0#
0&
#80
0"
0%
#85
b10 *
b11 (
1"
1%
1#
1&
#90
0"
0%
#95
b1 (
b11 *
1"
1%
#100
0"
0%
#105
b1 *
1"
1%
#110
0"
0%
#115
1"
1%
#120
0"
0%
#125
b10 (
1"
1%
0#
0&
#130
0"
0%
#135
b10 *
b11 (
1"
1%
1#
1&
#140
0"
0%
#145
b1 (
b11 *
1"
1%
#150
0"
0%
#155
b1 *
1"
1%
#160
0"
0%
#165
1"
1%
#170
0"
0%
#175
1"
1%
#180
0"
0%
#185
b10 (
1"
1%
0#
0&
#190
0"
0%
#195
b10 *
b11 (
1"
1%
1#
1&
#200
0"
0%
#205
b11 *
b100 (
1"
1%
0#
0&
#210
0"
0%
#215
1)
1!
b100 *
b1 (
1"
1%
1#
1&
#220
0"
0%
#225
b1 *
b10 (
0)
0!
1"
1%
0#
0&
#230
0"
0%
#235
b0 (
b10 *
1"
1%
#240
0"
0%
#245
b0 *
1"
1%
